data_parser/DataSource.py
data_parser/__init__.py
data_parser-0.0.3.dist-info/LICENSE
data_parser-0.0.3.dist-info/METADATA
data_parser-0.0.3.dist-info/WHEEL
data_parser-0.0.3.dist-info/top_level.txt
data_parser-0.0.3.dist-info/RECORD
