Metadata-Version: 2.1
Name: data-parser
Version: 0.0.3
Summary: Data parser to parse newline delimited logs into tabular format.
Home-page: UNKNOWN
Author: Lee Zhi Yong
Author-email: zhiyongengineering@email.com
License: UNKNOWN
Platform: UNKNOWN
Classifier: Programming Language :: Python :: 3
Classifier: Development Status :: 3 - Alpha
Classifier: Intended Audience :: Developers
Classifier: License :: OSI Approved :: MIT License
Requires-Python: >=3
Requires-Dist: pandas
Provides-Extra: pyspark
Requires-Dist: pyspark ; extra == 'pyspark'
